gun_scraper/__init__.py
gun_scraper/__main__.py
gun_scraper/file_io.py
gun_scraper/notifier.py
gun_scraper/scrapers/__init__.py
gun_scraper/scrapers/jaktmarken.py
gun_scraper/scrapers/jg.py
gun_scraper/scrapers/scraper_abc.py
gun_scraper/scrapers/torsbo.py
gun_scraper/utils.py
gun_scraper-0.2.1.dist-info/LICENSE
gun_scraper-0.2.1.dist-info/WHEEL
gun_scraper-0.2.1.dist-info/entry_points.txt
gun_scraper-0.2.1.dist-info/METADATA
gun_scraper-0.2.1.dist-info/RECORD
