Metadata-Version: 2.1
Name: gun-scraper
Version: 0.2.1
Summary: A simple scraper for finding guns, according to search criteria, from Swedish gun shops
Home-page: https://github.com/95ep/GunScraper
License: MIT
Author: Erik Persson
Author-email: erik.ao.persson@gmail.com
Requires-Python: >=3.9,<4.0
Classifier: Development Status :: 4 - Beta
Classifier: License :: OSI Approved :: MIT License
Classifier: Programming Language :: Python
Classifier: Programming Language :: Python :: 3
Classifier: Programming Language :: Python :: 3.9
Classifier: Programming Language :: Python :: 3.10
Classifier: Programming Language :: Python :: 3.11
Classifier: Programming Language :: Python :: 3
Requires-Dist: beautifulsoup4 (>=4.11.1,<5.0.0)
Requires-Dist: loguru (>=0.6.0,<0.7.0)
Requires-Dist: pyyaml (>=6.0,<7.0)
Requires-Dist: requests (>=2.28.1,<3.0.0)
